cwmath/__init__.py
cwmath/cwexamples.py
cwmath/cwplane3d.py
cwmath/cwvector3d.py
cwmath-0.0.9.dist-info/LICENSE
cwmath-0.0.9.dist-info/METADATA
cwmath-0.0.9.dist-info/WHEEL
cwmath-0.0.9.dist-info/top_level.txt
cwmath-0.0.9.dist-info/RECORD
