Metadata-Version: 2.1
Name: cwmath
Version: 0.0.9
Summary: Cadwork Math Utilities
Author-email: Cadwork <it@cadwork.ca>
License: MIT License
Project-URL: Homepage, https://github.com/cwapi3d/cwmath
Keywords: cadwork
Classifier: Development Status :: 3 - Alpha
Classifier: Environment :: Plugins
Classifier: Intended Audience :: Developers
Classifier: License :: OSI Approved :: MIT License
Classifier: Operating System :: Microsoft :: Windows
Classifier: Programming Language :: Python :: 3
Classifier: Programming Language :: Python :: 3.10
Classifier: Topic :: Software Development :: Libraries
Requires-Python: >=3.10
License-File: LICENSE
